flash_rwkv/__init__.py
flash_rwkv/rwkv5/__init__.py
flash_rwkv/rwkv5/wkv5_kernel.cu
flash_rwkv/rwkv5/wkv5_op.cpp
flash_rwkv/rwkv5/wkv5_op.py
flash_rwkv/rwkv6/__init__.py
flash_rwkv/rwkv6/wkv6_kernel.cu
flash_rwkv/rwkv6/wkv6_op.cpp
flash_rwkv/rwkv6/wkv6_op.py
flash_rwkv-0.3.0.dist-info/METADATA
flash_rwkv-0.3.0.dist-info/WHEEL
flash_rwkv-0.3.0.dist-info/top_level.txt
flash_rwkv-0.3.0.dist-info/RECORD
