Metadata-Version: 2.1
Name: flash-rwkv
Version: 0.3.0
Requires-Dist: torch (>=1.13.0)
